usleep_api/__init__.py
usleep_api/usleep_api.py
usleep_api/usleep_cmd.py
usleep_api/utils.py
usleep_api/version.py
usleep_api-0.1.2.dist-info/LICENSE
usleep_api-0.1.2.dist-info/METADATA
usleep_api-0.1.2.dist-info/WHEEL
usleep_api-0.1.2.dist-info/entry_points.txt
usleep_api-0.1.2.dist-info/top_level.txt
usleep_api-0.1.2.dist-info/RECORD
