Metadata-Version: 2.1
Name: usleep-api
Version: 0.1.2
Summary: Python bindings to the U-Sleep web API.
Home-page: https://github.com/perslev/U-Sleep-API-Python-Bindings
Author: Mathias Perslev
Author-email: map@di.ku.dk
License: UNKNOWN
Platform: UNKNOWN
Classifier: Environment :: Console
Classifier: Programming Language :: Python :: 3.6
Classifier: Programming Language :: Python :: 3.7
Classifier: Programming Language :: Python :: 3.8
Classifier: Programming Language :: Python :: 3.9
License-File: LICENSE
Requires-Dist: requests (==2.25.1)
